[
    {
        "hot_name": "V2EX",
        "content": [
            {
                "title": "首付不够，有什么靠谱的借钱渠道吗",
                "href": "https://www.v2ex.com/t/870798#reply106"
            },
            {
                "title": "一个大龄大厂搬砖工的叹息",
                "href": "https://www.v2ex.com/t/870825#reply100"
            },
            {
                "title": "程序员区提到的“内存”不应该默认是“memory”吗",
                "href": "https://www.v2ex.com/t/870855#reply96"
            },
            {
                "title": "辞职了，想问问去哪旅行好？",
                "href": "https://www.v2ex.com/t/870834#reply77"
            },
            {
                "title": "请教一下，前端真的会有算法诉求吗？",
                "href": "https://www.v2ex.com/t/870826#reply70"
            },
            {
                "title": "妙控板个人向劝退解毒",
                "href": "https://www.v2ex.com/t/870807#reply64"
            },
            {
                "title": "windows 11 bug 真的多到一言难尽啊",
                "href": "https://www.v2ex.com/t/870816#reply46"
            },
            {
                "title": "老板给了个 PHP 的网站包, 让我部署一下, 是部署到 apche 还是 nginx 好呢?",
                "href": "https://www.v2ex.com/t/870894#reply41"
            },
            {
                "title": "如何定义，初 中 高 级开发？",
                "href": "https://www.v2ex.com/t/870818#reply40"
            },
            {
                "title": "交流下大上行的家宽，收集与推荐",
                "href": "https://www.v2ex.com/t/870861#reply36"
            },
            {
                "title": "广州的二楼能不能租哇",
                "href": "https://www.v2ex.com/t/870794#reply35"
            },
            {
                "title": "Spotify 有必要开会员吗，一年 98 值不值",
                "href": "https://www.v2ex.com/t/870803#reply34"
            },
            {
                "title": "联通 1000M 宽带 插网线后 SpeedTest 下载速度只能跑到 940Mbps 左右",
                "href": "https://www.v2ex.com/t/870915#reply33"
            },
            {
                "title": "社保医保公积金什么的又调整了，到手工资还少了。",
                "href": "https://www.v2ex.com/t/870878#reply33"
            },
            {
                "title": "这两种变量名你们喜欢哪种？",
                "href": "https://www.v2ex.com/t/870886#reply33"
            },
            {
                "title": "有没有办法禁止健康宝扫码后的语音播报？",
                "href": "https://www.v2ex.com/t/870776#reply32"
            },
            {
                "title": "大家昨天(七夕)收到了什么礼物",
                "href": "https://www.v2ex.com/t/870895#reply31"
            },
            {
                "title": "求助电视盒子去 VIP、免费观看的方法",
                "href": "https://www.v2ex.com/t/870822#reply29"
            },
            {
                "title": "爱喝咖啡，但是牙齿容易变黄怎么办？",
                "href": "https://www.v2ex.com/t/870870#reply27"
            },
            {
                "title": "笔记本维修厮说，进水本很大概率会成为炸弹机，在未来某一天，发生奇怪故障。",
                "href": "https://www.v2ex.com/t/870799#reply26"
            },
            {
                "title": "I5-12600KF | 升级老式台式机，装机小白自己写了个清单，求大佬帮忙过目",
                "href": "https://www.v2ex.com/t/870873#reply26"
            },
            {
                "title": "WireGuard 远程组网的问题",
                "href": "https://www.v2ex.com/t/870792#reply25"
            },
            {
                "title": "求推荐工作无线鼠标， windows，前进后退切换按钮，静止时自动省电",
                "href": "https://www.v2ex.com/t/870877#reply25"
            },
            {
                "title": "为了方便看房价趋势弄了个 Chrome 插件，有关注房价的可以试用一下",
                "href": "https://www.v2ex.com/t/870841#reply24"
            },
            {
                "title": "迫于跑路，招个游戏服务器开发",
                "href": "https://www.v2ex.com/t/870847#reply24"
            },
            {
                "title": "git commit 经常出现的 chore 字眼是什么意思",
                "href": "https://www.v2ex.com/t/870808#reply23"
            },
            {
                "title": "想支持 Telegram，又感觉太贵，开通了土区 Tele 会员",
                "href": "https://www.v2ex.com/t/870809#reply22"
            },
            {
                "title": "Java 转 Go",
                "href": "https://www.v2ex.com/t/870824#reply22"
            },
            {
                "title": "求推荐几张永久或卡期内免年费的信用卡",
                "href": "https://www.v2ex.com/t/870913#reply21"
            },
            {
                "title": "手贱把 iPhone SE2 放鱼缸里降温",
                "href": "https://www.v2ex.com/t/870931#reply20"
            },
            {
                "title": "MacBook Pro (15-inch, 2018) 想换 M1",
                "href": "https://www.v2ex.com/t/870846#reply20"
            },
            {
                "title": "关于一个\"后台管理系统快速生成器\"的思路探讨",
                "href": "https://www.v2ex.com/t/870930#reply19"
            },
            {
                "title": "怎么用电视接链接书房电脑玩 steam 游戏",
                "href": "https://www.v2ex.com/t/870823#reply19"
            },
            {
                "title": "被百度智能云威胁了怎么办？",
                "href": "https://www.v2ex.com/t/870854#reply19"
            },
            {
                "title": "有感而发，一起旅行是考验男生能否安排好一切的吗？",
                "href": "https://www.v2ex.com/t/870943#reply18"
            },
            {
                "title": "不玩游戏买 6800H 的集显，建议 ThinkBook 14p 还是 YOGA pro 14s ？",
                "href": "https://www.v2ex.com/t/870785#reply18"
            },
            {
                "title": "寻找北京摩托车轻松骑行朋友",
                "href": "https://www.v2ex.com/t/870796#reply17"
            }
        ]
    },
    {
        "hot_name": "知乎热榜",
        "content": [
            {
                "title": "外交部宣布针对佩洛西窜台 8 项反制措施，会产生哪些影响，还有哪些信息值得关注？                --5974 万热度",
                "href": "https://www.zhihu.com/question/547135232"
            },
            {
                "title": "专家称「解放军联合演训随时可转为实战」，这意味着什么？此次解放军联合演训具有哪些重大意义？                --3628 万热度",
                "href": "https://www.zhihu.com/question/547091365"
            },
            {
                "title": "8 月 4 日全台「警政系统」深夜瘫痪，警员称「勤务停摆近 3 小时」，对岛内造成了哪些影响？                --1857 万热度",
                "href": "https://www.zhihu.com/question/547076277"
            },
            {
                "title": "中方宣布对佩洛西实施制裁，这意味着什么，还有哪些信息值得关注？                --982 万热度",
                "href": "https://www.zhihu.com/question/547123176"
            },
            {
                "title": "外交部表示中国的身后是 160 多个国家，共同站在公平正义一边，此次「佩洛西窜台」事件反映出哪些问题？                --698 万热度",
                "href": "https://www.zhihu.com/question/547155656"
            },
            {
                "title": "8 月 5 日美军派出至少 7 架各型侦察机前往台湾周边海域，如何看待其这一举动？                --419 万热度",
                "href": "https://www.zhihu.com/question/547091082"
            },
            {
                "title": "白宫官员表示「美国军方最近几周将通过海空路线穿越台湾海峡」，哪些信息需要关注？                --381 万热度",
                "href": "https://www.zhihu.com/question/547086210"
            },
            {
                "title": "8 月 4 日，美国官员在发布会称「大陆对台当局策略是煮青蛙」，这一表态透露了哪些信息？                --343 万热度",
                "href": "https://www.zhihu.com/question/547122506"
            },
            {
                "title": "东部战区发布「飞行员俯瞰宝岛海岸线和中央山脉」视频，释放了什么信号？有哪些信息值得注意？                --276 万热度",
                "href": "https://www.zhihu.com/question/547155707"
            },
            {
                "title": "如何看待外交部回应「中方同美日外长就台湾问题激烈交锋」，称「中方对不实信息进行有力批驳，捍卫了主权」？                --270 万热度",
                "href": "https://www.zhihu.com/question/547121923"
            },
            {
                "title": "江西上饶一区规定商家门头招牌不能出现经营内容，城管局回应称统一规定，不针对任何企业，如何看待这一做法？                --265 万热度",
                "href": "https://www.zhihu.com/question/547059085"
            },
            {
                "title": "美国以「为避免对华紧张关系升级」为由推迟「民兵 3」洲际弹道导弹试射，有哪些信息值得关注？                --264 万热度",
                "href": "https://www.zhihu.com/question/547103993"
            },
            {
                "title": "如何看待「岛内开始担心，美日韩等没有军事介入此次大陆军演，那以后也不会管了」？还有哪些信息值得注意？                --250 万热度",
                "href": "https://www.zhihu.com/question/547131605"
            },
            {
                "title": "如何看待云南某地卖房又现奇招，宣布可先买一半产权？                --202 万热度",
                "href": "https://www.zhihu.com/question/546892819"
            },
            {
                "title": "三亚本轮疫情是奥密克戎变异株 BA.5.1.3，系我国首次检出，这一变异株有何特点？较此前有哪些区别？                --151 万热度",
                "href": "https://www.zhihu.com/question/547048768"
            },
            {
                "title": "华春莹透露，王毅出席东亚系列外长会期间，没有会见美国务卿布林肯的计划，对此如何解读？                --141 万热度",
                "href": "https://www.zhihu.com/question/546586753"
            },
            {
                "title": "《明日战记》耗资巨大，票房能否突破 20 亿？                --132 万热度",
                "href": "https://www.zhihu.com/question/545378462"
            },
            {
                "title": "中国的 5A 景区放在全世界的名胜古迹中也是顶尖水准吗？                --127 万热度",
                "href": "https://www.zhihu.com/question/486958116"
            },
            {
                "title": "想买一台新车，孩子已上大学，存款 110 万无贷款，房子两套，每年 25 万左右家庭收入，买什么价位的合适？                --107 万热度",
                "href": "https://www.zhihu.com/question/546080687"
            },
            {
                "title": "解放军在台湾周边的六个海空区域大规模实弹演习，都投入了哪些武器？                --103 万热度",
                "href": "https://www.zhihu.com/question/547044621"
            },
            {
                "title": "常导火力突击，全部精准命中目标，如何评价我军的精确打击和区域拒止能力？                --99 万热度",
                "href": "https://www.zhihu.com/question/547001747"
            },
            {
                "title": "外交部就 G7 涉台声明召见有关驻华使节「同中方建交的国家不得与台湾官方往来」，释放了哪些信号？                --88 万热度",
                "href": "https://www.zhihu.com/question/547075870"
            },
            {
                "title": "电影《独行月球》中独孤月应不应该折返回去救袋鼠？                --88 万热度",
                "href": "https://www.zhihu.com/question/546273137"
            },
            {
                "title": "考研政治如何上 80?                --66 万热度",
                "href": "https://www.zhihu.com/question/381427168"
            },
            {
                "title": "如何评价《乘风破浪》第十二期（总决赛）？                --64 万热度",
                "href": "https://www.zhihu.com/question/547143182"
            },
            {
                "title": "有哪些自行车知识和技能是新手骑行前一定要熟练掌握的？                --59 万热度",
                "href": "https://www.zhihu.com/question/546278589"
            },
            {
                "title": "月薪 4 万人民币是一种怎样的感受？                --56 万热度",
                "href": "https://www.zhihu.com/question/36996031"
            },
            {
                "title": "如何理解「配置没输过，体验没赢过」这句话呢？                --48 万热度",
                "href": "https://www.zhihu.com/question/542153781"
            },
            {
                "title": "阿里巴巴 2023 年第一财季营收 2055.6 亿元，有哪些信息值得关注？                --47 万热度",
                "href": "https://www.zhihu.com/question/546972618"
            },
            {
                "title": "为什么《富爸爸穷爸爸》里说：「储蓄是失败者所为」？                --41 万热度",
                "href": "https://www.zhihu.com/question/543614412"
            },
            {
                "title": "如何看待美国务卿称「美国的一个中国政策没有改变，美国不支持『台独』」？                --41 万热度",
                "href": "https://www.zhihu.com/question/547115987"
            },
            {
                "title": "东部战区总医院开展实战化卫勤演练，首次使用动车组作为「卫生列车」，哪些信息值得关注？                --39 万热度",
                "href": "https://www.zhihu.com/question/547112578"
            },
            {
                "title": "赵丽颖的新剧《幸福到万家》为什么没火？                --37 万热度",
                "href": "https://www.zhihu.com/question/540950098"
            },
            {
                "title": "请问长焦镜头大光圈更重要还是防抖更重要?                --36 万热度",
                "href": "https://www.zhihu.com/question/546363670"
            },
            {
                "title": "为什么所有的人际关系里，只要我不主动就没有人主动找我?                --36 万热度",
                "href": "https://www.zhihu.com/question/498191369"
            },
            {
                "title": "该不该让小孩子在幼儿园学小学的知识？                --36 万热度",
                "href": "https://www.zhihu.com/question/46464362"
            },
            {
                "title": "蔚小理 2022 年 7 月交付数全面下滑，零跑哪吒埃安销量冲高，如何看待国内新能源汽车的销量表现？                --36 万热度",
                "href": "https://www.zhihu.com/question/546536981"
            },
            {
                "title": "书荒了怎么办，推荐一下最近你看的几本书?                --36 万热度",
                "href": "https://www.zhihu.com/question/546833314"
            },
            {
                "title": "豆腐都有哪些「0 失败」的懒人做法？                --36 万热度",
                "href": "https://www.zhihu.com/question/542322476"
            },
            {
                "title": "比亚迪宣布进入德国瑞典市场，你认为比亚迪在欧洲的发展前景如何？比亚迪如何和其他欧洲品牌竞争？                --36 万热度",
                "href": "https://www.zhihu.com/question/546580822"
            },
            {
                "title": "游戏制作成本为什么那么大？                --35 万热度",
                "href": "https://www.zhihu.com/question/23979766"
            },
            {
                "title": "想要进日企，日语至少得达到什么水平？                --35 万热度",
                "href": "https://www.zhihu.com/question/545400968"
            },
            {
                "title": "人类有希望走出银河系吗?                --35 万热度",
                "href": "https://www.zhihu.com/question/517090467"
            },
            {
                "title": "如何评价漫画《一人之下》587（626）话?                --34 万热度",
                "href": "https://www.zhihu.com/question/547013702"
            },
            {
                "title": "外卖和做饭到底哪个更加适合上班族？                --34 万热度",
                "href": "https://www.zhihu.com/question/439666029"
            },
            {
                "title": "8 月 5 日我国成功发射可重复使用试验航天器，有怎样的意义？                --34 万热度",
                "href": "https://www.zhihu.com/question/547043431"
            },
            {
                "title": "为什么我这么高三这么努力，没日没夜起早贪黑的学习，没考出成绩，他们就以一句没学评价？                --34 万热度",
                "href": "https://www.zhihu.com/question/540621480"
            },
            {
                "title": "错题本怎么做省时间？                --34 万热度",
                "href": "https://www.zhihu.com/question/35049882"
            },
            {
                "title": "水浒传中如果你是杨志，会怎么押送生辰纲?                --34 万热度",
                "href": "https://www.zhihu.com/question/334013108"
            },
            {
                "title": "九十年代，啤酒瓶还有人回收，为什么现在没人要了，资源更多了吗？                --33 万热度",
                "href": "https://www.zhihu.com/question/542755973"
            }
        ]
    },
    {
        "hot_name": "GitHub",
        "content": [
            {
                "title": "moyix /\n\n      fauxpilot---FauxPilot - an open-source GitHub Copilot server",
                "href": "https://github.com//moyix/fauxpilot"
            },
            {
                "title": "NVIDIAGameWorks /\n\n      kaolin-wisp---NVIDIA Kaolin Wisp is a PyTorch library powered by NVIDIA Kaolin Core to work with neural fields (including NeRFs, NGLOD, instant-ngp and VQAD).",
                "href": "https://github.com//NVIDIAGameWorks/kaolin-wisp"
            },
            {
                "title": "kamranahmedse /\n\n      developer-roadmap---Roadmap to becoming a developer in 2022",
                "href": "https://github.com//kamranahmedse/developer-roadmap"
            },
            {
                "title": "microsoft /\n\n      PowerToys---Windows system utilities to maximize productivity",
                "href": "https://github.com//microsoft/PowerToys"
            },
            {
                "title": "elastic /\n\n      protections-artifacts---Elastic Security detection content for Endpoint",
                "href": "https://github.com//elastic/protections-artifacts"
            },
            {
                "title": "sobinge /\n\n      2022-HW-POC---2022 护网行动 POC 整理",
                "href": "https://github.com//sobinge/2022-HW-POC"
            },
            {
                "title": "Asabeneh /\n\n      30-Days-Of-JavaScript---30 days of JavaScript programming challenge is a step-by-step guide to learn JavaScript programming language in 30 days. This challenge may take more than 100 days, please just follow your own pace.",
                "href": "https://github.com//Asabeneh/30-Days-Of-JavaScript"
            },
            {
                "title": "antoniosarosi /\n\n      Wallpapers---",
                "href": "https://github.com//antoniosarosi/Wallpapers"
            },
            {
                "title": "CodeEditApp /\n\n      CodeEdit---CodeEdit App for macOS – Elevate your code editing experience. Open source, free forever.",
                "href": "https://github.com//CodeEditApp/CodeEdit"
            },
            {
                "title": "HeliXonProtein /\n\n      OmegaFold---OmegaFold Release Code",
                "href": "https://github.com//HeliXonProtein/OmegaFold"
            },
            {
                "title": "UxxHans /\n\n      Rainbow-Cats-Personal-WeChat-MiniProgram---给女朋友做的微信小程序！情侣自己的任务和商城系统！",
                "href": "https://github.com//UxxHans/Rainbow-Cats-Personal-WeChat-MiniProgram"
            },
            {
                "title": "HVML /\n\n      PurC---The prime HVML interpreter for C Language.",
                "href": "https://github.com//HVML/PurC"
            },
            {
                "title": "golang /\n\n      go---The Go programming language",
                "href": "https://github.com//golang/go"
            },
            {
                "title": "YDHCUI /\n\n      manjusaka---牛屎花 一款C2远控",
                "href": "https://github.com//YDHCUI/manjusaka"
            },
            {
                "title": "public-apis /\n\n      public-apis---A collective list of free APIs",
                "href": "https://github.com//public-apis/public-apis"
            },
            {
                "title": "toeverything /\n\n      AFFiNE---There can be more than Notion and Miro. Affine is a next-gen knowledge base that brings planning, sorting and creating all together. Privacy first, open-source, customizable and ready to use.",
                "href": "https://github.com//toeverything/AFFiNE"
            },
            {
                "title": "cri-o /\n\n      cri-o---Open Container Initiative-based implementation of Kubernetes Container Runtime Interface",
                "href": "https://github.com//cri-o/cri-o"
            },
            {
                "title": "99designs /\n\n      gqlgen---go generate based graphql server library",
                "href": "https://github.com//99designs/gqlgen"
            },
            {
                "title": "facebook /\n\n      facebook-ios-sdk---Used to integrate the Facebook Platform with your iOS & tvOS apps.",
                "href": "https://github.com//facebook/facebook-ios-sdk"
            },
            {
                "title": "jgraph /\n\n      drawio-desktop---Official electron build of draw.io",
                "href": "https://github.com//jgraph/drawio-desktop"
            },
            {
                "title": "flutter /\n\n      flutter---Flutter makes it easy and fast to build beautiful apps for mobile and beyond",
                "href": "https://github.com//flutter/flutter"
            },
            {
                "title": "willwulfken /\n\n      MidJourney-Styles-and-Keywords-Reference---A reference containing Styles and Keywords that you can use with MidJourney AI. There are also pages showing resolution comparison, image weights, and much more!",
                "href": "https://github.com//willwulfken/MidJourney-Styles-and-Keywords-Reference"
            },
            {
                "title": "snipe /\n\n      snipe-it---A free open source IT asset/license management system",
                "href": "https://github.com//snipe/snipe-it"
            },
            {
                "title": "adiwajshing /\n\n      Baileys---Lightweight full-featured WhatsApp Web + Multi-Device API",
                "href": "https://github.com//adiwajshing/Baileys"
            },
            {
                "title": "Textualize /\n\n      textual---Textual is a TUI (Text User Interface) framework for Python inspired by modern web development.",
                "href": "https://github.com//Textualize/textual"
            }
        ]
    },
    {
        "hot_name": "贴吧",
        "content": [
            {
                "title": "中方宣布制裁佩洛西",
                "href": "http://tieba.baidu.com/hottopic/browse/hottopic?topic_id=7096138&topic_name=%E4%B8%AD%E6%96%B9%E5%AE%A3%E5%B8%83%E5%88%B6%E8%A3%81%E4%BD%A9%E6%B4%9B%E8%A5%BF"
            },
            {
                "title": "BLG战胜OMG",
                "href": "http://tieba.baidu.com/hottopic/browse/hottopic?topic_id=7099087&topic_name=BLG%E6%88%98%E8%83%9COMG"
            },
            {
                "title": "地图可显示台湾省每个街道",
                "href": "http://tieba.baidu.com/hottopic/browse/hottopic?topic_id=7094186&topic_name=%E5%9C%B0%E5%9B%BE%E5%8F%AF%E6%98%BE%E7%A4%BA%E5%8F%B0%E6%B9%BE%E7%9C%81%E6%AF%8F%E4%B8%AA%E8%A1%97%E9%81%93"
            },
            {
                "title": "美国推迟洲际弹道导弹试射",
                "href": "http://tieba.baidu.com/hottopic/browse/hottopic?topic_id=7096132&topic_name=%E7%BE%8E%E5%9B%BD%E6%8E%A8%E8%BF%9F%E6%B4%B2%E9%99%85%E5%BC%B9%E9%81%93%E5%AF%BC%E5%BC%B9%E8%AF%95%E5%B0%84"
            },
            {
                "title": "轰20被曝参与台湾军演",
                "href": "http://tieba.baidu.com/hottopic/browse/hottopic?topic_id=7096990&topic_name=%E8%BD%B020%E8%A2%AB%E6%9B%9D%E5%8F%82%E4%B8%8E%E5%8F%B0%E6%B9%BE%E5%86%9B%E6%BC%94"
            },
            {
                "title": "RNG造成比赛流程拖延被处罚",
                "href": "http://tieba.baidu.com/hottopic/browse/hottopic?topic_id=7096534&topic_name=RNG%E9%80%A0%E6%88%90%E6%AF%94%E8%B5%9B%E6%B5%81%E7%A8%8B%E6%8B%96%E5%BB%B6%E8%A2%AB%E5%A4%84%E7%BD%9A"
            },
            {
                "title": "解放军常规导弹首次穿越台湾岛",
                "href": "http://tieba.baidu.com/hottopic/browse/hottopic?topic_id=7090023&topic_name=%E8%A7%A3%E6%94%BE%E5%86%9B%E5%B8%B8%E8%A7%84%E5%AF%BC%E5%BC%B9%E9%A6%96%E6%AC%A1%E7%A9%BF%E8%B6%8A%E5%8F%B0%E6%B9%BE%E5%B2%9B"
            },
            {
                "title": "LGD 0-2 TES",
                "href": "http://tieba.baidu.com/hottopic/browse/hottopic?topic_id=7098873&topic_name=LGD%200-2%20TES"
            },
            {
                "title": "《绝区零》首测开启",
                "href": "http://tieba.baidu.com/hottopic/browse/hottopic?topic_id=7096130&topic_name=%E3%80%8A%E7%BB%9D%E5%8C%BA%E9%9B%B6%E3%80%8B%E9%A6%96%E6%B5%8B%E5%BC%80%E5%90%AF"
            },
            {
                "title": "美特斯邦威被曝大量拖欠工资",
                "href": "http://tieba.baidu.com/hottopic/browse/hottopic?topic_id=7096249&topic_name=%E7%BE%8E%E7%89%B9%E6%96%AF%E9%82%A6%E5%A8%81%E8%A2%AB%E6%9B%9D%E5%A4%A7%E9%87%8F%E6%8B%96%E6%AC%A0%E5%B7%A5%E8%B5%84"
            },
            {
                "title": "东部战区实弹发射训练任务圆满完成",
                "href": "http://tieba.baidu.com/hottopic/browse/hottopic?topic_id=7080072&topic_name=%E4%B8%9C%E9%83%A8%E6%88%98%E5%8C%BA%E5%AE%9E%E5%BC%B9%E5%8F%91%E5%B0%84%E8%AE%AD%E7%BB%83%E4%BB%BB%E5%8A%A1%E5%9C%86%E6%BB%A1%E5%AE%8C%E6%88%90"
            },
            {
                "title": "蔡依林一天掉粉30万",
                "href": "http://tieba.baidu.com/hottopic/browse/hottopic?topic_id=7096129&topic_name=%E8%94%A1%E4%BE%9D%E6%9E%97%E4%B8%80%E5%A4%A9%E6%8E%89%E7%B2%8930%E4%B8%87"
            },
            {
                "title": "LadyGaga确认主演小丑2",
                "href": "http://tieba.baidu.com/hottopic/browse/hottopic?topic_id=7093960&topic_name=LadyGaga%E7%A1%AE%E8%AE%A4%E4%B8%BB%E6%BC%94%E5%B0%8F%E4%B8%912"
            },
            {
                "title": "华科大女生出轨43岁副主任",
                "href": "http://tieba.baidu.com/hottopic/browse/hottopic?topic_id=7096131&topic_name=%E5%8D%8E%E7%A7%91%E5%A4%A7%E5%A5%B3%E7%94%9F%E5%87%BA%E8%BD%A843%E5%B2%81%E5%89%AF%E4%B8%BB%E4%BB%BB"
            },
            {
                "title": "枪杀安倍嫌犯或被判无期",
                "href": "http://tieba.baidu.com/hottopic/browse/hottopic?topic_id=7094877&topic_name=%E6%9E%AA%E6%9D%80%E5%AE%89%E5%80%8D%E5%AB%8C%E7%8A%AF%E6%88%96%E8%A2%AB%E5%88%A4%E6%97%A0%E6%9C%9F"
            },
            {
                "title": "安以轩老公被正式起诉",
                "href": "http://tieba.baidu.com/hottopic/browse/hottopic?topic_id=7086892&topic_name=%E5%AE%89%E4%BB%A5%E8%BD%A9%E8%80%81%E5%85%AC%E8%A2%AB%E6%AD%A3%E5%BC%8F%E8%B5%B7%E8%AF%89"
            },
            {
                "title": "美女博主学历被打假",
                "href": "http://tieba.baidu.com/hottopic/browse/hottopic?topic_id=7077651&topic_name=%E7%BE%8E%E5%A5%B3%E5%8D%9A%E4%B8%BB%E5%AD%A6%E5%8E%86%E8%A2%AB%E6%89%93%E5%81%87"
            },
            {
                "title": "今年七夕晚会打几分",
                "href": "http://tieba.baidu.com/hottopic/browse/hottopic?topic_id=7093824&topic_name=%E4%BB%8A%E5%B9%B4%E4%B8%83%E5%A4%95%E6%99%9A%E4%BC%9A%E6%89%93%E5%87%A0%E5%88%86"
            },
            {
                "title": "宝可梦新款游戏遭群嘲",
                "href": "http://tieba.baidu.com/hottopic/browse/hottopic?topic_id=7080854&topic_name=%E5%AE%9D%E5%8F%AF%E6%A2%A6%E6%96%B0%E6%AC%BE%E6%B8%B8%E6%88%8F%E9%81%AD%E7%BE%A4%E5%98%B2"
            }
        ]
    },
    {
        "hot_name": "新浪微博",
        "content": [
            {
                "title": "[置顶]#打卡中国#",
                "href": "https://s.weibo.com/weibo?q=%23打卡中国%23"
            },
            {
                "title": "1.取消安排中美两军战区领导通话",
                "href": "https://s.weibo.com/weibo?q=%23取消安排中美两军战区领导通话%23"
            },
            {
                "title": "2.那英 成了团没什么用",
                "href": "https://s.weibo.com/weibo?q=%23那英 成了团没什么用%23"
            },
            {
                "title": "3.东部战区出动海陆空英雄部队",
                "href": "https://s.weibo.com/weibo?q=%23东部战区出动海陆空英雄部队%23"
            },
            {
                "title": "4.华为MateBook X Pro开售",
                "href": "https://s.weibo.com/weibo?q=%23华为MateBook X Pro开售%23"
            },
            {
                "title": "5.女子耳朵痛痒难耐拆开枕头全是虫",
                "href": "https://s.weibo.com/weibo?q=%23女子耳朵痛痒难耐拆开枕头全是虫%23"
            },
            {
                "title": "6.外交部宣布制裁佩洛西",
                "href": "https://s.weibo.com/weibo?q=%23外交部宣布制裁佩洛西%23"
            },
            {
                "title": "7.王心凌 乘风破浪年度总冠军",
                "href": "https://s.weibo.com/weibo?q=%23王心凌 乘风破浪年度总冠军%23"
            },
            {
                "title": "8.日本碰瓷中国导弹毫无道理",
                "href": "https://s.weibo.com/weibo?q=%23日本碰瓷中国导弹毫无道理%23"
            },
            {
                "title": "9.如愿 好好哭",
                "href": "https://s.weibo.com/weibo?q=%23如愿 好好哭%23"
            },
            {
                "title": "10.空军飞行员目视距离俯瞰祖国宝岛",
                "href": "https://s.weibo.com/weibo?q=%23空军飞行员目视距离俯瞰祖国宝岛%23"
            },
            {
                "title": "11.日本外相发言时中俄外长同时离席退场",
                "href": "https://s.weibo.com/weibo?q=%23日本外相发言时中俄外长同时离席退场%23"
            },
            {
                "title": "12.王毅说很久没听到美国说这种话了",
                "href": "https://s.weibo.com/weibo?q=%23王毅说很久没听到美国说这种话了%23"
            },
            {
                "title": "13.再也不敢在朋友圈emo了",
                "href": "https://s.weibo.com/weibo?q=%23再也不敢在朋友圈emo了%23"
            },
            {
                "title": "14.成都税务部门调查彩虹夫妇",
                "href": "https://s.weibo.com/weibo?q=%23成都税务部门调查彩虹夫妇%23"
            },
            {
                "title": "15.日本领导人在台湾问题上表现非常不好",
                "href": "https://s.weibo.com/weibo?q=%23日本领导人在台湾问题上表现非常不好%23"
            },
            {
                "title": "16.郑秀妍看郑秀晶VCR泪崩",
                "href": "https://s.weibo.com/weibo?q=%23郑秀妍看郑秀晶VCR泪崩%23"
            },
            {
                "title": "17.母亲以死逼迫女儿与相亲对象结婚",
                "href": "https://s.weibo.com/weibo?q=%23母亲以死逼迫女儿与相亲对象结婚%23"
            },
            {
                "title": "18.乘风破浪全场大合唱下一站天后",
                "href": "https://s.weibo.com/weibo?q=%23乘风破浪全场大合唱下一站天后%23"
            },
            {
                "title": "19.姜广涛将进酒广播剧暂停更新",
                "href": "https://s.weibo.com/weibo?q=%23姜广涛将进酒广播剧暂停更新%23"
            },
            {
                "title": "20.外交部回应中方同美日外长激烈交锋",
                "href": "https://s.weibo.com/weibo?q=%23外交部回应中方同美日外长激烈交锋%23"
            },
            {
                "title": "21.驻欧盟使团发言人正告七国集团",
                "href": "https://s.weibo.com/weibo?q=%23驻欧盟使团发言人正告七国集团%23"
            },
            {
                "title": "22.赵露思迪士尼",
                "href": "https://s.weibo.com/weibo?q=%23赵露思迪士尼%23"
            },
            {
                "title": "23.Twins下一站天后 爷青回",
                "href": "https://s.weibo.com/weibo?q=%23Twins下一站天后 爷青回%23"
            },
            {
                "title": "24.中国好声音",
                "href": "https://s.weibo.com/weibo?q=%23中国好声音%23"
            },
            {
                "title": "25.我军在台岛周边演训是否会常态化",
                "href": "https://s.weibo.com/weibo?q=%23我军在台岛周边演训是否会常态化%23"
            },
            {
                "title": "26.北京拟试点老年人贷款买房",
                "href": "https://s.weibo.com/weibo?q=%23北京拟试点老年人贷款买房%23"
            },
            {
                "title": "27.山东热成灿东了",
                "href": "https://s.weibo.com/weibo?q=%23山东热成灿东了%23"
            },
            {
                "title": "28.彩虹夫妇账号绑定企业仅7人参保",
                "href": "https://s.weibo.com/weibo?q=%23彩虹夫妇账号绑定企业仅7人参保%23"
            },
            {
                "title": "29.民警在嫌疑人孩子面前藏起手铐",
                "href": "https://s.weibo.com/weibo?q=%23民警在嫌疑人孩子面前藏起手铐%23"
            },
            {
                "title": "30.日本最没资格就涉台问题指手画脚",
                "href": "https://s.weibo.com/weibo?q=%23日本最没资格就涉台问题指手画脚%23"
            },
            {
                "title": "31.美方称大陆对台当局策略是煮青蛙",
                "href": "https://s.weibo.com/weibo?q=%23美方称大陆对台当局策略是煮青蛙%23"
            },
            {
                "title": "32.沙溢认出赵丽颖没认出胡可",
                "href": "https://s.weibo.com/weibo?q=%23沙溢认出赵丽颖没认出胡可%23"
            },
            {
                "title": "33.有点儿意思",
                "href": "https://s.weibo.com/weibo?q=%23有点儿意思%23"
            },
            {
                "title": "34.张子枫张新成海边吻戏",
                "href": "https://s.weibo.com/weibo?q=%23张子枫张新成海边吻戏%23"
            },
            {
                "title": "35.东部战区继续进行实战化联合演训",
                "href": "https://s.weibo.com/weibo?q=%23东部战区继续进行实战化联合演训%23"
            },
            {
                "title": "36.阿娇 这个夏天有阿Sa有你们值了",
                "href": "https://s.weibo.com/weibo?q=%23阿娇 这个夏天有阿Sa有你们值了%23"
            },
            {
                "title": "37.华春莹质问美方早知如此何必当初",
                "href": "https://s.weibo.com/weibo?q=%23华春莹质问美方早知如此何必当初%23"
            },
            {
                "title": "38.东部战区继续位台岛周边联合演训",
                "href": "https://s.weibo.com/weibo?q=%23东部战区继续位台岛周边联合演训%23"
            },
            {
                "title": "39.中国手机出货量或跌至10年来最低",
                "href": "https://s.weibo.com/weibo?q=%23中国手机出货量或跌至10年来最低%23"
            },
            {
                "title": "40.三亚新增189例确诊",
                "href": "https://s.weibo.com/weibo?q=%23三亚新增189例确诊%23"
            },
            {
                "title": "41.最想打卡的台湾景点",
                "href": "https://s.weibo.com/weibo?q=%23最想打卡的台湾景点%23"
            },
            {
                "title": "42.黄子韬一号线艺人给你们表演个节目",
                "href": "https://s.weibo.com/weibo?q=%23黄子韬一号线艺人给你们表演个节目%23"
            },
            {
                "title": "43.乘风破浪3个人喜爱度总榜",
                "href": "https://s.weibo.com/weibo?q=%23乘风破浪3个人喜爱度总榜%23"
            },
            {
                "title": "44.昆凌说应该不会再生了",
                "href": "https://s.weibo.com/weibo?q=%23昆凌说应该不会再生了%23"
            },
            {
                "title": "45.永劫无间炸服",
                "href": "https://s.weibo.com/weibo?q=%23永劫无间炸服%23"
            },
            {
                "title": "46.外交部回应中俄外长在日本外相发言时离席",
                "href": "https://s.weibo.com/weibo?q=%23外交部回应中俄外长在日本外相发言时离席%23"
            },
            {
                "title": "47.百度地图被搜崩了",
                "href": "https://s.weibo.com/weibo?q=%23百度地图被搜崩了%23"
            },
            {
                "title": "48.eStar对战GK",
                "href": "https://s.weibo.com/weibo?q=%23eStar对战GK%23"
            },
            {
                "title": "49.美特斯邦威被曝大量拖欠工资",
                "href": "https://s.weibo.com/weibo?q=%23美特斯邦威被曝大量拖欠工资%23"
            },
            {
                "title": "50.时间真的会消磨爱意吗",
                "href": "https://s.weibo.com/weibo?q=%23时间真的会消磨爱意吗%23"
            },
            {
                "title": "51.郑州房地产纾困基金暂定规模100亿",
                "href": "https://s.weibo.com/weibo?q=%23郑州房地产纾困基金暂定规模100亿%23"
            }
        ]
    },
    {
        "hot_name": "云音乐飙升榜",
        "content": [
            {
                "title": "当",
                "href": "https://music.163.com/#/song?id=1969061662"
            },
            {
                "title": "阴天快乐",
                "href": "https://music.163.com/#/song?id=1968053454"
            },
            {
                "title": "星汉游",
                "href": "https://music.163.com/#/song?id=1969030824"
            },
            {
                "title": "七夕",
                "href": "https://music.163.com/#/song?id=28953350"
            },
            {
                "title": "对你说",
                "href": "https://music.163.com/#/song?id=1968508691"
            },
            {
                "title": "Angel",
                "href": "https://music.163.com/#/song?id=1969270025"
            },
            {
                "title": "遗失的心跳(完整版)",
                "href": "https://music.163.com/#/song?id=1966155051"
            },
            {
                "title": "夏日潮汐",
                "href": "https://music.163.com/#/song?id=1968040792"
            },
            {
                "title": "不太周的情歌",
                "href": "https://music.163.com/#/song?id=1969030965"
            },
            {
                "title": "想你想你想我",
                "href": "https://music.163.com/#/song?id=1876226709"
            },
            {
                "title": "下一个天亮",
                "href": "https://music.163.com/#/song?id=1958150862"
            },
            {
                "title": "混蛋男人",
                "href": "https://music.163.com/#/song?id=1967794601"
            },
            {
                "title": "Bones",
                "href": "https://music.163.com/#/song?id=1927389937"
            },
            {
                "title": "给你一瓶魔法药水",
                "href": "https://music.163.com/#/song?id=1959667345"
            },
            {
                "title": "就是爱你",
                "href": "https://music.163.com/#/song?id=1878315329"
            },
            {
                "title": "想你想你",
                "href": "https://music.163.com/#/song?id=569212210"
            },
            {
                "title": "比月亮浪漫",
                "href": "https://music.163.com/#/song?id=1965921146"
            },
            {
                "title": "范进中举",
                "href": "https://music.163.com/#/song?id=1858118347"
            },
            {
                "title": "依然爱你",
                "href": "https://music.163.com/#/song?id=1363657770"
            },
            {
                "title": "字母鞋",
                "href": "https://music.163.com/#/song?id=1966206678"
            },
            {
                "title": "暖暖",
                "href": "https://music.163.com/#/song?id=1968773532"
            },
            {
                "title": "等雨，等你",
                "href": "https://music.163.com/#/song?id=1969049532"
            },
            {
                "title": "ชอบเธออะ",
                "href": "https://music.163.com/#/song?id=1968032170"
            },
            {
                "title": "玻璃心",
                "href": "https://music.163.com/#/song?id=1956766760"
            },
            {
                "title": "不跟你好了",
                "href": "https://music.163.com/#/song?id=1427444926"
            },
            {
                "title": "Dancing With A Stranger",
                "href": "https://music.163.com/#/song?id=1338962014"
            },
            {
                "title": "月亮里的玫瑰与故事",
                "href": "https://music.163.com/#/song?id=1961506634"
            },
            {
                "title": "苦茶子",
                "href": "https://music.163.com/#/song?id=1922888354"
            },
            {
                "title": "这是我一生中最勇敢的瞬间",
                "href": "https://music.163.com/#/song?id=1366216050"
            },
            {
                "title": "Bones",
                "href": "https://music.163.com/#/song?id=1960362416"
            },
            {
                "title": "Cure For Me",
                "href": "https://music.163.com/#/song?id=1859515946"
            },
            {
                "title": "未出现传闻",
                "href": "https://music.163.com/#/song?id=1964380663"
            },
            {
                "title": "我们的爱 (Live)",
                "href": "https://music.163.com/#/song?id=530057158"
            },
            {
                "title": "唯一",
                "href": "https://music.163.com/#/song?id=1807799505"
            },
            {
                "title": "心动告白",
                "href": "https://music.163.com/#/song?id=1966912032"
            },
            {
                "title": "Afterthought",
                "href": "https://music.163.com/#/song?id=1481691186"
            },
            {
                "title": "良辰今夕",
                "href": "https://music.163.com/#/song?id=1969250367"
            },
            {
                "title": "是你",
                "href": "https://music.163.com/#/song?id=1969246603"
            },
            {
                "title": "在你的身边",
                "href": "https://music.163.com/#/song?id=475479888"
            },
            {
                "title": "TERAK",
                "href": "https://music.163.com/#/song?id=1959166451"
            },
            {
                "title": "披星戴月的想你",
                "href": "https://music.163.com/#/song?id=1317457805"
            },
            {
                "title": "心动一夏",
                "href": "https://music.163.com/#/song?id=1961712419"
            },
            {
                "title": "雨中漫步",
                "href": "https://music.163.com/#/song?id=1928380645"
            },
            {
                "title": "喜欢你",
                "href": "https://music.163.com/#/song?id=28949444"
            },
            {
                "title": "温柔",
                "href": "https://music.163.com/#/song?id=386538"
            },
            {
                "title": "带我去找夜生活",
                "href": "https://music.163.com/#/song?id=1410647903"
            },
            {
                "title": "如果的事 (男声版)",
                "href": "https://music.163.com/#/song?id=1969039800"
            },
            {
                "title": "长相思",
                "href": "https://music.163.com/#/song?id=1969298047"
            },
            {
                "title": "愛你",
                "href": "https://music.163.com/#/song?id=1961971680"
            },
            {
                "title": "黑乌鸦和少女",
                "href": "https://music.163.com/#/song?id=1410707394"
            },
            {
                "title": "半山腰",
                "href": "https://music.163.com/#/song?id=1965555401"
            },
            {
                "title": "一百个字",
                "href": "https://music.163.com/#/song?id=1968752864"
            },
            {
                "title": "给你呀（又名：for ya）",
                "href": "https://music.163.com/#/song?id=1497588709"
            },
            {
                "title": "小宇",
                "href": "https://music.163.com/#/song?id=185712"
            },
            {
                "title": "那么骄傲",
                "href": "https://music.163.com/#/song?id=247864"
            },
            {
                "title": "没遇见更好",
                "href": "https://music.163.com/#/song?id=1956302525"
            },
            {
                "title": "Star Unkind (Lanfranchi & Farina Radio)",
                "href": "https://music.163.com/#/song?id=512640293"
            },
            {
                "title": "YOU SO DONE",
                "href": "https://music.163.com/#/song?id=1473832380"
            },
            {
                "title": "溯 (Reverse)",
                "href": "https://music.163.com/#/song?id=1294951288"
            },
            {
                "title": "三得利",
                "href": "https://music.163.com/#/song?id=1324874010"
            },
            {
                "title": "橘子日落",
                "href": "https://music.163.com/#/song?id=1488288293"
            },
            {
                "title": "Bones",
                "href": "https://music.163.com/#/song?id=1968973437"
            },
            {
                "title": "dio cantando2.000",
                "href": "https://music.163.com/#/song?id=1927119452"
            },
            {
                "title": "灰色人生",
                "href": "https://music.163.com/#/song?id=1968662854"
            },
            {
                "title": "我们打着光脚在风车下跑，手上的狗尾巴草摇啊摇",
                "href": "https://music.163.com/#/song?id=1968035768"
            },
            {
                "title": "剩下的盛夏",
                "href": "https://music.163.com/#/song?id=34228130"
            },
            {
                "title": "今年一定带你去看海",
                "href": "https://music.163.com/#/song?id=1939457246"
            },
            {
                "title": "桃花诺",
                "href": "https://music.163.com/#/song?id=480579393"
            },
            {
                "title": "遗失的心跳",
                "href": "https://music.163.com/#/song?id=306877"
            },
            {
                "title": "我的美丽",
                "href": "https://music.163.com/#/song?id=1901319325"
            },
            {
                "title": "台本",
                "href": "https://music.163.com/#/song?id=1881218945"
            },
            {
                "title": "头号傻瓜",
                "href": "https://music.163.com/#/song?id=1958419043"
            },
            {
                "title": "Shadow of the Sun",
                "href": "https://music.163.com/#/song?id=28411642"
            },
            {
                "title": "夏至未至",
                "href": "https://music.163.com/#/song?id=482999696"
            },
            {
                "title": "明天",
                "href": "https://music.163.com/#/song?id=1844448536"
            },
            {
                "title": "Happiness",
                "href": "https://music.163.com/#/song?id=1968952431"
            },
            {
                "title": "Ass Like That",
                "href": "https://music.163.com/#/song?id=1948083890"
            },
            {
                "title": "Sunroof",
                "href": "https://music.163.com/#/song?id=1893514633"
            },
            {
                "title": "风雨飘洒",
                "href": "https://music.163.com/#/song?id=1961566389"
            },
            {
                "title": "爱在晚秋之前",
                "href": "https://music.163.com/#/song?id=1888412536"
            },
            {
                "title": "凛冬将至(Winter Is Coming)",
                "href": "https://music.163.com/#/song?id=1314931825"
            },
            {
                "title": "偷走你的心",
                "href": "https://music.163.com/#/song?id=1406648894"
            },
            {
                "title": "特别的人",
                "href": "https://music.163.com/#/song?id=28403111"
            },
            {
                "title": "妈妈的歌谣",
                "href": "https://music.163.com/#/song?id=29122797"
            },
            {
                "title": "全世界陪我失眠",
                "href": "https://music.163.com/#/song?id=1306507727"
            },
            {
                "title": "我要你",
                "href": "https://music.163.com/#/song?id=488641895"
            },
            {
                "title": "霓虹甜心",
                "href": "https://music.163.com/#/song?id=1329719698"
            },
            {
                "title": "爱人错过",
                "href": "https://music.163.com/#/song?id=1368754688"
            },
            {
                "title": "idontwannabeyouanymore",
                "href": "https://music.163.com/#/song?id=493448423"
            },
            {
                "title": "City Of Stars (From \"La La Land\" Soundtrack)",
                "href": "https://music.163.com/#/song?id=456370728"
            },
            {
                "title": "Feel Right Now (feat. Nonô)",
                "href": "https://music.163.com/#/song?id=1451122329"
            },
            {
                "title": "呼吸决定",
                "href": "https://music.163.com/#/song?id=35678875"
            },
            {
                "title": "夏日大冒险",
                "href": "https://music.163.com/#/song?id=1967737946"
            },
            {
                "title": "她来听我的演唱会",
                "href": "https://music.163.com/#/song?id=188647"
            },
            {
                "title": "影",
                "href": "https://music.163.com/#/song?id=1967771605"
            },
            {
                "title": "Fahrenheit",
                "href": "https://music.163.com/#/song?id=1811351751"
            },
            {
                "title": "第一次爱情",
                "href": "https://music.163.com/#/song?id=1968781668"
            },
            {
                "title": "有你的快乐",
                "href": "https://music.163.com/#/song?id=28432278"
            },
            {
                "title": "晚婚 (Live)",
                "href": "https://music.163.com/#/song?id=1336789771"
            }
        ]
    },
    {
        "hot_name": "豆瓣",
        "content": [
            {
                "title": "【科普】饮食、绝育与行为对小狗寿命的影响",
                "href": "https://www.douban.com/group/topic/271996873/"
            },
            {
                "title": "廊下漏日光，片片若白雪。",
                "href": "https://www.douban.com/group/topic/272005619/"
            },
            {
                "title": "高中考得差的时候，我就在校门口躺着",
                "href": "https://www.douban.com/group/topic/271874162/"
            },
            {
                "title": "无油烟版好吃惨了的荞麦凉面",
                "href": "https://www.douban.com/group/topic/271929027/"
            },
            {
                "title": "A Room of My Own，湖边夏日小家",
                "href": "https://www.douban.com/group/topic/271870753/"
            },
            {
                "title": "一个书里学到的正念抗焦虑技巧",
                "href": "https://www.douban.com/group/topic/271934338/"
            },
            {
                "title": "读研MEME",
                "href": "https://www.douban.com/group/topic/271883091/"
            },
            {
                "title": "考研政治80+经验分享",
                "href": "https://www.douban.com/group/topic/271629689/"
            },
            {
                "title": "说说你们知道的健身小tips，帮助新人小白少走弯路（评论整理持续更新）",
                "href": "https://www.douban.com/group/topic/271679859/"
            },
            {
                "title": "上课走错教室…老师讲了五分钟后发现她也走错了……",
                "href": "https://www.douban.com/group/topic/271650012/"
            },
            {
                "title": "切开柠檬的一瞬间，被可爱暴击",
                "href": "https://www.douban.com/group/topic/271519693/"
            },
            {
                "title": "为什么东西方用的颜文字不一样",
                "href": "https://www.douban.com/group/topic/271384346/"
            },
            {
                "title": "厦门的风藏在柯达胶卷里面！",
                "href": "https://www.douban.com/group/topic/271433614/"
            },
            {
                "title": "个人小技巧：提高做 word/ppt 效率、提高学习效率",
                "href": "https://www.douban.com/group/topic/271407259/"
            },
            {
                "title": "小森林般的家 一个人夏日宅家好惬意",
                "href": "https://www.douban.com/group/topic/271461397/"
            },
            {
                "title": "呜呜呜我妈妈真的好甜",
                "href": "https://www.douban.com/group/topic/271410548/"
            },
            {
                "title": "家里蹲的我们能做些什么？",
                "href": "https://www.douban.com/group/topic/271476085/"
            },
            {
                "title": "有没有乐队小猫系列头像",
                "href": "https://www.douban.com/group/topic/271211066/"
            },
            {
                "title": "修改简历思路tips",
                "href": "https://www.douban.com/group/topic/271167747/"
            },
            {
                "title": "将洗衣液倒进了洗衣粉里意外冲出了蓝天白云🥫",
                "href": "https://www.douban.com/group/topic/271152102/"
            },
            {
                "title": "我爸练字",
                "href": "https://www.douban.com/group/topic/271119314/"
            },
            {
                "title": "欢迎云做客我的原木风顶楼复式小屋",
                "href": "https://www.douban.com/group/topic/271152456/"
            },
            {
                "title": "作为资深留学生的一点忠告",
                "href": "https://www.douban.com/group/topic/271136152/"
            },
            {
                "title": "一个人走新疆西藏(进行中)",
                "href": "https://www.douban.com/group/topic/271061464/"
            },
            {
                "title": "薄荷茉莉冰美式🥳真的超好喝",
                "href": "https://www.douban.com/group/topic/271045289/"
            },
            {
                "title": "扒拉了这几年买过觉得好用的东西【很杂，啥都有】",
                "href": "https://www.douban.com/group/topic/271046534/"
            },
            {
                "title": "上海看展｜徐冰的语言",
                "href": "https://www.douban.com/group/topic/271105674/"
            },
            {
                "title": "关于书籍折角磕碰修复的一些经验分享",
                "href": "https://www.douban.com/group/topic/271066111/"
            },
            {
                "title": "坐蒸汽火车上山 (Brienzer Rothorn)",
                "href": "https://www.douban.com/group/topic/271096891/"
            },
            {
                "title": "藏在爆米花里的萌犬",
                "href": "https://www.douban.com/group/topic/271087241/"
            }
        ]
    },
    {
        "hot_name": "天涯",
        "content": [
            {
                "title": "[生活那点事]女友请男摄影师拍私房照？男盆友表示：三观震碎，你能接受吗？ ",
                "href": "http://bbs.tianya.cn/post-1095-864962-1.shtml"
            },
            {
                "title": "[情感天地]离异单身十年，遭遇60岁的“普信男” ",
                "href": "http://bbs.tianya.cn/post-feeling-4556807-1.shtml"
            },
            {
                "title": "[重庆]给重庆主城区二孩家庭算笔账！ ",
                "href": "http://bbs.tianya.cn/post-45-1830944-1.shtml"
            },
            {
                "title": "[婆媳关系]暑假带老公孩子回娘家住，我妈肠胃炎，弟媳做饭菜不高兴 ",
                "href": "http://bbs.tianya.cn/post-934-239250-1.shtml"
            },
            {
                "title": "[三亚]这次三亚传播的新冠毒株是最强传播力的毒株，也是国内第一次发现的毒株 ",
                "href": "http://bbs.tianya.cn/post-73-669057-1.shtml"
            },
            {
                "title": "[房产观澜]房子太多卖不出去怎么办 ",
                "href": "http://bbs.tianya.cn/post-house-789747-1.shtml"
            },
            {
                "title": "[饮食男女]记录我的生活和不足为外人道的碎碎念 ",
                "href": "http://bbs.tianya.cn/post-96-928656-1.shtml"
            },
            {
                "title": "[台湾风云]大家好~我是台灣人 ",
                "href": "http://bbs.tianya.cn/post-333-1564709-1.shtml"
            },
            {
                "title": "[饮食男女]碌碌半生尚还行，“人间有味是清欢“”，哈哈，认真排版重新开贴 ",
                "href": "http://bbs.tianya.cn/post-96-928635-1.shtml"
            },
            {
                "title": "[生活那点事]而今何事最相宜? 宜醉宜游宜睡。 ",
                "href": "http://bbs.tianya.cn/post-1095-864877-1.shtml"
            },
            {
                "title": "[贴图专区]一位从来没有画过画的老人画的老人题材画 ",
                "href": "http://bbs.tianya.cn/post-no04-2847212-1.shtml"
            },
            {
                "title": "[旅游休闲]带10岁娃徒步虎跳峡、雨崩村记录 ",
                "href": "http://bbs.tianya.cn/post-travel-865128-1.shtml"
            },
            {
                "title": "[关天茶舍]七夕节是个什么节 ",
                "href": "http://bbs.tianya.cn/post-no01-537475-1.shtml"
            },
            {
                "title": "[天涯摄影]小米10手机里的城市记忆[置顶推荐] ",
                "href": "http://bbs.tianya.cn/post-tianyaphoto-141852-1.shtml"
            },
            {
                "title": "[煮酒论史]《宋朝那些事呀》（第一部连载到宋朝开国） ",
                "href": "http://bbs.tianya.cn/post-no05-526434-1.shtml"
            },
            {
                "title": "[天涯杂谈]你介意你家小区外开殡葬用品店吗？【讨论】 ",
                "href": "http://bbs.tianya.cn/post-free-6210267-1.shtml"
            },
            {
                "title": "[家有学童]暴脾气妈妈记录慢腾腾娃的初中生活（2022-2025） ",
                "href": "http://bbs.tianya.cn/post-767-54518-1.shtml"
            },
            {
                "title": "[天涯杂谈]江西一男子幼儿园行凶致3死6伤，警方正在追捕江西幼儿园行凶男子【关注】 ",
                "href": "http://bbs.tianya.cn/post-free-6210289-1.shtml"
            },
            {
                "title": "[情感天地]未婚妻要求把钱给她管理 ",
                "href": "http://bbs.tianya.cn/post-feeling-4556744-1.shtml"
            },
            {
                "title": "[旅游休闲]大美新疆，我的北疆之旅 ",
                "href": "http://bbs.tianya.cn/post-travel-865126-1.shtml"
            },
            {
                "title": "[汽车时代]献计我国汽车产业发展【讨论】 ",
                "href": "http://bbs.tianya.cn/post-cars-489738-1.shtml"
            },
            {
                "title": "[我的大学]我们家孩子在一所民大学，现已降级两次，下学期面临劝退，家里不知怎么办 ",
                "href": "http://bbs.tianya.cn/post-university-1199675-1.shtml"
            },
            {
                "title": "[海外华人]记录厄瓜多尔生活点滴【New】 ",
                "href": "http://bbs.tianya.cn/post-outseachina-132166-1.shtml"
            },
            {
                "title": "[海口]国庆放假7天上班7天是一种什么体验 ",
                "href": "http://bbs.tianya.cn/post-40-783936-1.shtml"
            },
            {
                "title": "[家有学童]青春期孩子初升高，老父亲老母亲怎么教育呀？都来唠唠~ ",
                "href": "http://bbs.tianya.cn/post-767-54546-1.shtml"
            },
            {
                "title": "[亲子中心]一个经历二次离异，二次产后抑郁症的单亲妈妈 ",
                "href": "http://bbs.tianya.cn/post-98-1223109-1.shtml"
            },
            {
                "title": "[娱乐八卦]刷到百花奖的票数，是认真的吗？ ",
                "href": "http://bbs.tianya.cn/post-funinfo-7943047-1.shtml"
            },
            {
                "title": "[婆媳关系]现在全社会素质和治安都提高了，以前炫富容易有人身危险，说说一些炫富被害的案例 ",
                "href": "http://bbs.tianya.cn/post-934-239219-1.shtml"
            },
            {
                "title": "[家居装饰]记录我的江南小城叠拼装修之路 ",
                "href": "http://bbs.tianya.cn/post-766-533487-1.shtml"
            },
            {
                "title": "[生活那点事]请别叫我大婶儿 ",
                "href": "http://bbs.tianya.cn/post-1095-864875-1.shtml"
            },
            {
                "title": "[天涯杂谈]藏区女同志的乡镇工作日记 ",
                "href": "http://bbs.tianya.cn/post-free-6191216-1.shtml"
            },
            {
                "title": "[房产观澜]新一线东莞，接着奏乐接着舞 ",
                "href": "http://bbs.tianya.cn/post-house-789751-1.shtml"
            },
            {
                "title": "[愚人码头]【热帖】【聚焦首页】【谦翰画集】百幅扇面 ",
                "href": "http://bbs.tianya.cn/post-67-576027-1.shtml"
            },
            {
                "title": "[情感天地]单亲妈妈，如何熬过这一段～ ",
                "href": "http://bbs.tianya.cn/post-feeling-4556739-1.shtml"
            },
            {
                "title": "[娱乐八卦]从300w收获内娱糊咖塌房开始，带你盘点那些年内娱震撼过大众的数字 ",
                "href": "http://bbs.tianya.cn/post-funinfo-7943043-1.shtml"
            },
            {
                "title": "[]记录普通家庭或者底层人的生活，且家有两儿 ",
                "href": "http://bbs.tianya.cn/post-me-369172-1.shtml"
            },
            {
                "title": "[]陪伴老爸老妈的日子 ",
                "href": "http://bbs.tianya.cn/post-me-339775-1.shtml"
            },
            {
                "title": "[我的大学]2020--2028  向大学出发 ",
                "href": "http://bbs.tianya.cn/post-university-1199681-1.shtml"
            },
            {
                "title": "[三十不嫁]30岁以后的日子 ",
                "href": "http://bbs.tianya.cn/post-oldgirl-291941-1.shtml"
            },
            {
                "title": "[旅游休闲]西藏，西藏！ ",
                "href": "http://bbs.tianya.cn/post-travel-865065-1.shtml"
            },
            {
                "title": "[生活那点事]怀孕8个月，老公要跟我离婚 ",
                "href": "http://bbs.tianya.cn/post-1095-864841-1.shtml"
            },
            {
                "title": "[生活那点事]漂在广州 ",
                "href": "http://bbs.tianya.cn/post-1095-864871-1.shtml"
            },
            {
                "title": "[情感天地]丧偶马上5年了，想再婚，发现太难了？ ",
                "href": "http://bbs.tianya.cn/post-feeling-4556657-1.shtml"
            },
            {
                "title": "[天涯杂谈]疫情期间，老人下地打药被要求广播检讨10遍！【关注】 ",
                "href": "http://bbs.tianya.cn/post-free-6210340-1.shtml"
            },
            {
                "title": "[天涯杂谈]我对养庞物持反对态度 ",
                "href": "http://bbs.tianya.cn/post-free-6210225-1.shtml"
            },
            {
                "title": "[天涯杂谈]农村孩子，读书还能改变命运吗？【讨论】 ",
                "href": "http://bbs.tianya.cn/post-free-6210212-1.shtml"
            },
            {
                "title": "[天涯杂谈]安徽多地餐馆“拍黄瓜”被罚5千元？做凉菜要办证【关注】 ",
                "href": "http://bbs.tianya.cn/post-free-6210185-1.shtml"
            },
            {
                "title": "[婆媳关系]夫妻感情不和不一定是小三，有可能是他亲妈 ",
                "href": "http://bbs.tianya.cn/post-934-239186-1.shtml"
            },
            {
                "title": "[婆媳关系]姑姐要再住一个月，感觉自己是不是太小气了？ ",
                "href": "http://bbs.tianya.cn/post-934-239164-1.shtml"
            },
            {
                "title": "[生活那点事]70后单亲大妈生活琐事 ",
                "href": "http://bbs.tianya.cn/post-1095-864743-1.shtml"
            },
            {
                "title": "[天涯杂谈]毕业22岁女孩加班猝死，公司：没什么好说的！官方已介入调查！ ",
                "href": "http://bbs.tianya.cn/post-free-6210092-1.shtml"
            },
            {
                "title": "[天涯杂谈]为女儿上好大学“铺路” 银行行长上当26次被骗3.5亿元【关注】 ",
                "href": "http://bbs.tianya.cn/post-free-6209481-1.shtml"
            },
            {
                "title": "[家有学童]马上高二了，如何激发孩子的斗志？ ",
                "href": "http://bbs.tianya.cn/post-767-54526-1.shtml"
            },
            {
                "title": "[天涯杂谈]有一个人贩子婆婆是什么体验？？ ",
                "href": "http://bbs.tianya.cn/post-free-6209937-1.shtml"
            },
            {
                "title": "[天涯杂谈]尼姑实名举报某和尚对其威逼利诱潜规则，警方通报 ",
                "href": "http://bbs.tianya.cn/post-free-6209812-1.shtml"
            },
            {
                "title": "[情感天地]一个70后闯深圳的故事 ",
                "href": "http://bbs.tianya.cn/post-feeling-4556451-1.shtml"
            },
            {
                "title": "[娱乐八卦]周渝民夫妇被骗775万元：妻子高学历却很单纯，全职在家带6岁女儿 ",
                "href": "http://bbs.tianya.cn/post-funinfo-7943060-1.shtml"
            },
            {
                "title": "[生活那点事]儿子被上海交大录取了，学校劝他回去复读冲清华大学【讨论】 ",
                "href": "http://bbs.tianya.cn/post-1095-864650-1.shtml"
            },
            {
                "title": "[房产观澜]事实证明，房地产商和炒房客是一群喂不饱的狼。 ",
                "href": "http://bbs.tianya.cn/post-house-789651-1.shtml"
            },
            {
                "title": "[职场天地]被公司领导辞退了，不接受，又变成了降薪，我该怎么办？【讨论】 ",
                "href": "http://bbs.tianya.cn/post-no20-693202-1.shtml"
            },
            {
                "title": "[生活那点事]我们的生活 · 陪伴孩子复读的一年 ",
                "href": "http://bbs.tianya.cn/post-1095-864390-1.shtml"
            },
            {
                "title": "[国际观察]趣谈：英国为何表现得那么仇恨俄罗斯呢？ ",
                "href": "http://bbs.tianya.cn/post-worldlook-1977442-1.shtml"
            },
            {
                "title": "[天涯摄影]上世纪八九十年代的照片有种难以言表的生动和生活气息 ",
                "href": "http://bbs.tianya.cn/post-tianyaphoto-141850-1.shtml"
            },
            {
                "title": "[关天茶舍]中国农业必须走规模化、科技化、集约化的专业化协作发展道路 ",
                "href": "http://bbs.tianya.cn/post-no01-537345-1.shtml"
            },
            {
                "title": "[生活那点事]亲妹子的孩子一直在我家吃饭，我要管吗？ ",
                "href": "http://bbs.tianya.cn/post-1095-864595-1.shtml"
            },
            {
                "title": "[饮食男女]记录一下琐碎的生活 ",
                "href": "http://bbs.tianya.cn/post-96-928572-1.shtml"
            },
            {
                "title": "[职场天地]在亲戚公司上班的狗血故事 ",
                "href": "http://bbs.tianya.cn/post-no20-693285-1.shtml"
            },
            {
                "title": "[生活那点事]深圳到浙江的生活 ",
                "href": "http://bbs.tianya.cn/post-1095-864503-1.shtml"
            },
            {
                "title": "[天涯杂谈]今天无事，来说说内卷极其严重的南京中考吧 ",
                "href": "http://bbs.tianya.cn/post-free-6209307-1.shtml"
            },
            {
                "title": "[旅游休闲]从暹粒到清迈的一路光影记录 ",
                "href": "http://bbs.tianya.cn/post-travel-864995-1.shtml"
            },
            {
                "title": "[天涯杂谈]无论再出多少新闻事件，我们注意力都不应该从唐山转移——我的天涯大字报 ",
                "href": "http://bbs.tianya.cn/post-free-6209448-1.shtml"
            },
            {
                "title": "[房产观澜]小县城买了一堆房，没一套好的，悔死了 ",
                "href": "http://bbs.tianya.cn/post-house-789612-1.shtml"
            },
            {
                "title": "[贴图专区]农村老家建房记 1层 3室2厅2卫 ",
                "href": "http://bbs.tianya.cn/post-no04-2846969-1.shtml"
            },
            {
                "title": "[旅游休闲]《周游记》——2022暑假自驾游新疆 ",
                "href": "http://bbs.tianya.cn/post-travel-864925-1.shtml"
            },
            {
                "title": "[家有学童]以梦为马，不负韶华，记录女儿初二初三学习历程，与小孩一起进步，做成长型父母 ",
                "href": "http://bbs.tianya.cn/post-767-54481-1.shtml"
            },
            {
                "title": "[天涯杂谈]为安倍晋三“哭丧”的曾颖于19日在日本自杀！【讨论】 ",
                "href": "http://bbs.tianya.cn/post-free-6209723-1.shtml"
            },
            {
                "title": "[生活那点事]2022离开大城市，找个小县城过慢生活！ ",
                "href": "http://bbs.tianya.cn/post-1095-864626-1.shtml"
            },
            {
                "title": "[情感天地]时隔半年，我又偷看了老公的手机。睡不着，想聊聊。 ",
                "href": "http://bbs.tianya.cn/post-feeling-4556510-1.shtml"
            },
            {
                "title": "[天涯杂谈]将近40岁被学校扫地出门，没有退路可言——论“非升即走”制度【讨论】 ",
                "href": "http://bbs.tianya.cn/post-free-6209673-1.shtml"
            },
            {
                "title": "[情感天地]离婚2年了，有一个女儿，前夫一直想复婚，我应该复婚吗？ ",
                "href": "http://bbs.tianya.cn/post-feeling-4555791-1.shtml"
            },
            {
                "title": "[煮酒论史]面对列强兵败如山倒的清军，为何能以压倒性姿态收复新疆？ ",
                "href": "http://bbs.tianya.cn/post-no05-526358-1.shtml"
            },
            {
                "title": "[生活那点事]40岁丁克不婚族的退休日常 ",
                "href": "http://bbs.tianya.cn/post-1095-864095-1.shtml"
            },
            {
                "title": "[贴图专区]新买的1961年挂历，慢慢的回忆 ",
                "href": "http://bbs.tianya.cn/post-no04-2847023-1.shtml"
            },
            {
                "title": "[旅游休闲]人生初次，私奔远方—从北到南横穿中国5676公里行记 ",
                "href": "http://bbs.tianya.cn/post-travel-865074-1.shtml"
            },
            {
                "title": "[情感天地]老公无工作，是否还继续要小孩？ ",
                "href": "http://bbs.tianya.cn/post-feeling-4556588-1.shtml"
            },
            {
                "title": "[旅游休闲]这些年我们一起走过的地方--甘青大环线 ",
                "href": "http://bbs.tianya.cn/post-travel-865024-1.shtml"
            },
            {
                "title": "[情感天地]谈谈我对自己35岁依然单身的自我认识 ",
                "href": "http://bbs.tianya.cn/post-feeling-4556521-1.shtml"
            },
            {
                "title": "[婆媳关系]婆婆的养老问题该如何解决？才能兼顾好 ",
                "href": "http://bbs.tianya.cn/post-934-239080-1.shtml"
            },
            {
                "title": "[三亚]母亲要把自己的黑人孩子丢弃路上，被路人围堵。 ",
                "href": "http://bbs.tianya.cn/post-73-668957-1.shtml"
            },
            {
                "title": "[情感天地]36岁大龄女的迷茫，大概要孤独终老了吧 ",
                "href": "http://bbs.tianya.cn/post-feeling-4556486-1.shtml"
            },
            {
                "title": "[旅游休闲]2022游鄂西 ",
                "href": "http://bbs.tianya.cn/post-travel-864970-1.shtml"
            },
            {
                "title": "[情感天地]高原小城VS一线的双城记，记录简单粗暴的生活点滴 ",
                "href": "http://bbs.tianya.cn/post-feeling-4555526-1.shtml"
            },
            {
                "title": "[情感天地]媒人变成老公的暧昧对象，太让人痛苦了 ",
                "href": "http://bbs.tianya.cn/post-feeling-4556577-1.shtml"
            },
            {
                "title": "[家有学童]你是我的英雄-高中实践版（2022-2025） ",
                "href": "http://bbs.tianya.cn/post-767-54484-1.shtml"
            },
            {
                "title": "[国际观察]印度人口即将超越中国是件可怕的事情吗？ ",
                "href": "http://bbs.tianya.cn/post-worldlook-1977091-1.shtml"
            },
            {
                "title": "[旅游休闲]影像伦敦 ",
                "href": "http://bbs.tianya.cn/post-travel-865028-1.shtml"
            },
            {
                "title": "[饮食男女]悦悦的乡居生活 ",
                "href": "http://bbs.tianya.cn/post-96-928613-1.shtml"
            },
            {
                "title": "[贴图专区]中国出土玉器全集·pdf ",
                "href": "http://bbs.tianya.cn/post-no04-2847058-1.shtml"
            },
            {
                "title": "[长江杂谈]张小泉客服一场错误公关将个案变整体，普遍变独家【论坛首页推荐】 ",
                "href": "http://bbs.tianya.cn/post-26-542044-1.shtml"
            },
            {
                "title": "[红袖天涯]感兴趣的一起来接句玩：我偷了黄昏的酒 ",
                "href": "http://bbs.tianya.cn/post-1178-77597-1.shtml"
            }
        ]
    }
]